ladim_aggregate/__init__.py
ladim_aggregate/__main__.py
ladim_aggregate/geotag.py
ladim_aggregate/histogram.py
ladim_aggregate/input.py
ladim_aggregate/output.py
ladim_aggregate/parseconfig.py
ladim_aggregate/proj.py
ladim_aggregate/script.py
ladim_aggregate/examples/__init__.py
ladim_aggregate/examples/complex/__init__.py
ladim_aggregate/examples/complex/aggregate.yaml
ladim_aggregate/examples/complex/count.nc.yaml
ladim_aggregate/examples/complex/count_20190703000000_12345.nc.yaml
ladim_aggregate/examples/complex/count_20190703000000_12346.nc.yaml
ladim_aggregate/examples/complex/count_20200703000000_12345.nc.yaml
ladim_aggregate/examples/complex/count_20200703000000_12346.nc.yaml
ladim_aggregate/examples/complex/ladim_2019.nc.yaml
ladim_aggregate/examples/complex/ladim_2020.nc.yaml
ladim_aggregate/examples/connect/__init__.py
ladim_aggregate/examples/connect/aggregate.yaml
ladim_aggregate/examples/connect/count.nc.yaml
ladim_aggregate/examples/connect/ladim.nc.yaml
ladim_aggregate/examples/connect/regions.geojson
ladim_aggregate/examples/filter/__init__.py
ladim_aggregate/examples/filter/aggregate.yaml
ladim_aggregate/examples/filter/count.nc.yaml
ladim_aggregate/examples/filter/ladim.nc.yaml
ladim_aggregate/examples/grid_2D/__init__.py
ladim_aggregate/examples/grid_2D/aggregate.yaml
ladim_aggregate/examples/grid_2D/count.nc.yaml
ladim_aggregate/examples/grid_2D/ladim.nc.yaml
ladim_aggregate/examples/groupby/__init__.py
ladim_aggregate/examples/groupby/aggregate.yaml
ladim_aggregate/examples/groupby/count.nc.yaml
ladim_aggregate/examples/groupby/ladim.nc.yaml
ladim_aggregate/examples/multi/__init__.py
ladim_aggregate/examples/multi/aggregate.yaml
ladim_aggregate/examples/multi/count.nc.yaml
ladim_aggregate/examples/multi/count_12345.nc.yaml
ladim_aggregate/examples/multi/count_12346.nc.yaml
ladim_aggregate/examples/multi/ladim_2019.nc.yaml
ladim_aggregate/examples/multi/ladim_2020.nc.yaml
ladim_aggregate/examples/proj/__init__.py
ladim_aggregate-1.26.0.dist-info/LICENSE
ladim_aggregate-1.26.0.dist-info/METADATA
ladim_aggregate-1.26.0.dist-info/WHEEL
ladim_aggregate-1.26.0.dist-info/entry_points.txt
ladim_aggregate-1.26.0.dist-info/top_level.txt
ladim_aggregate-1.26.0.dist-info/RECORD
