Metadata-Version: 2.2
Name: ladim_aggregate
Version: 1.26.0
Summary: Aggregate tool for LADiM output files
Author: Pål Næverlid Sævik
Author-email: paal.naeverlid.saevik@hi.no
License: MIT
Requires-Python: >=3.7
License-File: LICENSE
Requires-Dist: numpy
Requires-Dist: pytest
Requires-Dist: xarray
Requires-Dist: netCDF4
Requires-Dist: PyYAML
Requires-Dist: pyproj
Requires-Dist: pandas
Requires-Dist: numexpr
Requires-Dist: scipy
Requires-Dist: matplotlib
